nsync_cli/__init__.py
nsync_cli/client.py
nsync_cli/client_commands.py
nsync_cli/config.py
nsync_cli/globber.py
nsync_cli/main.py
nsync_cli/queries/__init__.py
nsync_cli/queries/delete.py
nsync_cli/queries/exchange.py
nsync_cli/queries/file.py
nsync_cli/queries/login.py
nsync_cli/queries/user.py
nsync_cli-1.7.3.dist-info/entry_points.txt
nsync_cli-1.7.3.dist-info/WHEEL
nsync_cli-1.7.3.dist-info/METADATA
nsync_cli-1.7.3.dist-info/license_files/LICENSE
nsync_cli-1.7.3.dist-info/RECORD
