Metadata-Version: 2.1
Name: nsync-cli
Version: 1.7.3
Summary: NeutronSync command line client. Use to securely sync your dot files.
License: MIT
Author-email: Paul Bailey <paul@neutron.studio>
Requires-Python: >=3.7
Requires-Dist: cryptography~=3.4
Requires-Dist: httpx[brotli,http2]~=0.18
Requires-Dist: pendulum~=2.1
Requires-Dist: py-essentials~=1.4
Requires-Dist: tabulate~=0.8
Requires-Dist: three-merge~=0.1
Requires-Dist: typer~=0.3
Project-URL: homepage, https://github.com/neutron-sync/nsync-cli
